Metadata-Version: 2.3
Name: guidedchoice-pyctuator
Version: 1.2.2
Summary: A Python implementation of the Spring Actuator API for popular web frameworks (GuidedChoice fork)
Keywords: spring boot admin,actuator,pyctuator,fastapi,flask,aiohttp,tornado,guidedchoice
Author: Your Name
Author-email: your.email@guidedchoice.com
Maintainer: Your Name
Maintainer-email: your.email@guidedchoice.com
Requires-Python: >=3.9,<4.0
Classifier: Development Status :: 4 - Beta
Classifier: Environment :: Web Environment
Classifier: Framework :: FastAPI
Classifier: Framework :: Flask
Classifier: Framework :: aiohttp
Classifier: Intended Audience :: Developers
Classifier: License :: OSI Approved :: Apache Software License
Classifier: Programming Language :: Python :: 3
Classifier: Programming Language :: Python :: 3.9
Classifier: Programming Language :: Python :: 3.10
Classifier: Programming Language :: Python :: 3.11
Classifier: Programming Language :: Python :: 3.12
Classifier: Programming Language :: Python :: 3.13
Classifier: Topic :: Internet :: WWW/HTTP :: HTTP Servers
Classifier: Topic :: Internet :: WWW/HTTP :: WSGI :: Application
Classifier: Topic :: Software Development :: Libraries :: Python Modules
Classifier: Topic :: System :: Monitoring
Classifier: Typing :: Typed
Provides-Extra: aiohttp
Provides-Extra: db
Provides-Extra: fastapi
Provides-Extra: flask
Provides-Extra: psutil
Provides-Extra: redis
Provides-Extra: tornado
Requires-Dist: PyMySQL (>=1.0.2,<2.0.0) ; extra == "db"
Requires-Dist: aiohttp (>=3.6.2,<4.0.0) ; extra == "aiohttp"
Requires-Dist: cryptography (>=39.0.1,<40.0.0) ; extra == "db"
Requires-Dist: fastapi (>=0.100.1,<0.101.0) ; extra == "fastapi"
Requires-Dist: flask (>=2.3.0,<3.0.0) ; extra == "flask"
Requires-Dist: psutil (>=5.6,<6.0) ; extra == "psutil"
Requires-Dist: redis (>=4.3.4,<5.0.0) ; extra == "redis"
Requires-Dist: sqlalchemy (>=2.0.4,<3.0.0) ; extra == "db"
Requires-Dist: tornado (>=6.0.4,<7.0.0) ; extra == "tornado"
Requires-Dist: uvicorn (>=0.23.0,<0.24.0) ; extra == "fastapi"
Project-URL: Homepage, https://github.com/guidedchoice/pyctuator
Project-URL: Repository, https://github.com/guidedchoice/pyctuator
